{"createdAt":"2020-11-03T23:55:33.365-08:00","summary":{"DAVID ARAMBULA":2751,"LIANA LEBARON":3111,"GEORGE GASTIL":3317,"TERESA ROSIAK":2630},"results":[{"id":"504500","consName":"LEMON GROVE","candidate":"DAVID ARAMBULA","votes":1428},{"id":"504600","consName":"LEMON GROVE","candidate":"DAVID ARAMBULA","votes":1323},{"id":"999755","consName":"VBM-AV","candidate":"DAVID ARAMBULA","votes":0},{"id":"504500","consName":"LEMON GROVE","candidate":"LIANA LEBARON","votes":1665},{"id":"504600","consName":"LEMON GROVE","candidate":"LIANA LEBARON","votes":1444},{"id":"999755","consName":"VBM-AV","candidate":"LIANA LEBARON","votes":2},{"id":"504500","consName":"LEMON GROVE","candidate":"GEORGE GASTIL","votes":1636},{"id":"504600","consName":"LEMON GROVE","candidate":"GEORGE GASTIL","votes":1679},{"id":"999755","consName":"VBM-AV","candidate":"GEORGE GASTIL","votes":2},{"id":"504500","consName":"LEMON GROVE","candidate":"TERESA ROSIAK","votes":1381},{"id":"504600","consName":"LEMON GROVE","candidate":"TERESA ROSIAK","votes":1249},{"id":"999755","consName":"VBM-AV","candidate":"TERESA ROSIAK","votes":0}]}