{"createdAt":"2020-11-06T17:01:11.080-08:00","summary":{"ADRIAN ARANCIBIA":17073,"CINDY LOPEZ":12803,"SANDRA \"SANDI\" L. SMITH":6318},"results":[{"id":"501600","consName":"SPRING VALLEY","candidate":"ADRIAN ARANCIBIA","votes":69},{"id":"501720","consName":"SPRING VALLEY","candidate":"ADRIAN ARANCIBIA","votes":2210},{"id":"510720","consName":"BONITA","candidate":"ADRIAN ARANCIBIA","votes":458},{"id":"518800","consName":"NATIONAL CITY","candidate":"ADRIAN ARANCIBIA","votes":432},{"id":"525250","consName":"CHULA VISTA","candidate":"ADRIAN ARANCIBIA","votes":615},{"id":"525260","consName":"CHULA VISTA","candidate":"ADRIAN ARANCIBIA","votes":1511},{"id":"525400","consName":"CHULA VISTA","candidate":"ADRIAN ARANCIBIA","votes":784},{"id":"526410","consName":"CHULA VISTA","candidate":"ADRIAN ARANCIBIA","votes":1115},{"id":"527700","consName":"CHULA VISTA","candidate":"ADRIAN ARANCIBIA","votes":2134},{"id":"528820","consName":"CHULA VISTA","candidate":"ADRIAN ARANCIBIA","votes":744},{"id":"528900","consName":"CHULA VISTA","candidate":"ADRIAN ARANCIBIA","votes":314},{"id":"528960","consName":"CHULA VISTA","candidate":"ADRIAN ARANCIBIA","votes":1872},{"id":"529520","consName":"CHULA VISTA","candidate":"ADRIAN ARANCIBIA","votes":1953},{"id":"529810","consName":"CHULA VISTA","candidate":"ADRIAN ARANCIBIA","votes":1003},{"id":"530500","consName":"CHULA VISTA","candidate":"ADRIAN ARANCIBIA","votes":215},{"id":"530510","consName":"CHULA VISTA","candidate":"ADRIAN ARANCIBIA","votes":157},{"id":"532500","consName":"CHULA VISTA","candidate":"ADRIAN ARANCIBIA","votes":408},{"id":"532510","consName":"CHULA VISTA","candidate":"ADRIAN ARANCIBIA","votes":98},{"id":"532570","consName":"CHULA VISTA","candidate":"ADRIAN ARANCIBIA","votes":801},{"id":"999559","consName":"UNINCORPORATED-VBM","candidate":"ADRIAN ARANCIBIA","votes":86},{"id":"999566","consName":"CHULA VISTA-VBM","candidate":"ADRIAN ARANCIBIA","votes":0},{"id":"999567","consName":"CHULA VISTA-VBM","candidate":"ADRIAN ARANCIBIA","votes":0},{"id":"999568","consName":"CHULA VISTA-VBM","candidate":"ADRIAN ARANCIBIA","votes":0},{"id":"999569","consName":"CHULA VISTA-VBM","candidate":"ADRIAN ARANCIBIA","votes":1},{"id":"999574","consName":"CHULA VISTA-VBM","candidate":"ADRIAN ARANCIBIA","votes":0},{"id":"999575","consName":"CHULA VISTA-VBM","candidate":"ADRIAN ARANCIBIA","votes":0},{"id":"999579","consName":"NATIONAL CITY-VBM","candidate":"ADRIAN ARANCIBIA","votes":0},{"id":"999580","consName":"NATIONAL CITY-VBM","candidate":"ADRIAN ARANCIBIA","votes":36},{"id":"999594","consName":"UNINCORPORATED-VBM","candidate":"ADRIAN ARANCIBIA","votes":0},{"id":"999787","consName":"UNINCORPORATED-VBM","candidate":"ADRIAN ARANCIBIA","votes":0},{"id":"999789","consName":"UNINCORPORATED-VBM","candidate":"ADRIAN ARANCIBIA","votes":0},{"id":"999792","consName":"UNINCORPORATED-VBM","candidate":"ADRIAN ARANCIBIA","votes":0},{"id":"999797","consName":"CHULA VISTA-VBM","candidate":"ADRIAN ARANCIBIA","votes":13},{"id":"999798","consName":"CHULA VISTA-VBM","candidate":"ADRIAN ARANCIBIA","votes":0},{"id":"999799","consName":"CHULA VISTA-VBM","candidate":"ADRIAN ARANCIBIA","votes":0},{"id":"999807","consName":"UNINCORPORATED-VBM","candidate":"ADRIAN ARANCIBIA","votes":44},{"id":"999808","consName":"VBM-AV","candidate":"ADRIAN ARANCIBIA","votes":0},{"id":"999813","consName":"UNINCORPORATED-VBM","candidate":"ADRIAN ARANCIBIA","votes":0},{"id":"999817","consName":"UNINCORPORATED-VBM","candidate":"ADRIAN ARANCIBIA","votes":0},{"id":"999827","consName":"CHULA VISTA-VBM","candidate":"ADRIAN ARANCIBIA","votes":0},{"id":"999828","consName":"CHULA VISTA-VBM","candidate":"ADRIAN ARANCIBIA","votes":0},{"id":"999829","consName":"CHULA VISTA-VBM","candidate":"ADRIAN ARANCIBIA","votes":0},{"id":"999830","consName":"VBM-AV","candidate":"ADRIAN ARANCIBIA","votes":0},{"id":"999834","consName":"CHULA VISTA-VBM","candidate":"ADRIAN ARANCIBIA","votes":0},{"id":"999835","consName":"CHULA VISTA-VBM","candidate":"ADRIAN ARANCIBIA","votes":0},{"id":"999836","consName":"CHULA VISTA-VBM","candidate":"ADRIAN ARANCIBIA","votes":0},{"id":"999837","consName":"CHULA VISTA-VBM","candidate":"ADRIAN ARANCIBIA","votes":0},{"id":"999838","consName":"CHULA VISTA-VBM","candidate":"ADRIAN ARANCIBIA","votes":0},{"id":"999839","consName":"CHULA VISTA-VBM","candidate":"ADRIAN ARANCIBIA","votes":0},{"id":"501600","consName":"SPRING VALLEY","candidate":"CINDY LOPEZ","votes":72},{"id":"501720","consName":"SPRING VALLEY","candidate":"CINDY LOPEZ","votes":1455},{"id":"510720","consName":"BONITA","candidate":"CINDY LOPEZ","votes":302},{"id":"518800","consName":"NATIONAL CITY","candidate":"CINDY LOPEZ","votes":319},{"id":"525250","consName":"CHULA VISTA","candidate":"CINDY LOPEZ","votes":451},{"id":"525260","consName":"CHULA VISTA","candidate":"CINDY LOPEZ","votes":1210},{"id":"525400","consName":"CHULA VISTA","candidate":"CINDY LOPEZ","votes":525},{"id":"526410","consName":"CHULA VISTA","candidate":"CINDY LOPEZ","votes":882},{"id":"527700","consName":"CHULA VISTA","candidate":"CINDY LOPEZ","votes":1626},{"id":"528820","consName":"CHULA VISTA","candidate":"CINDY LOPEZ","votes":571},{"id":"528900","consName":"CHULA VISTA","candidate":"CINDY LOPEZ","votes":277},{"id":"528960","consName":"CHULA VISTA","candidate":"CINDY LOPEZ","votes":1225},{"id":"529520","consName":"CHULA VISTA","candidate":"CINDY LOPEZ","votes":1822},{"id":"529810","consName":"CHULA VISTA","candidate":"CINDY LOPEZ","votes":869},{"id":"530500","consName":"CHULA VISTA","candidate":"CINDY LOPEZ","votes":157},{"id":"530510","consName":"CHULA VISTA","candidate":"CINDY LOPEZ","votes":166},{"id":"532500","consName":"CHULA VISTA","candidate":"CINDY LOPEZ","votes":248},{"id":"532510","consName":"CHULA VISTA","candidate":"CINDY LOPEZ","votes":61},{"id":"532570","consName":"CHULA VISTA","candidate":"CINDY LOPEZ","votes":468},{"id":"999559","consName":"UNINCORPORATED-VBM","candidate":"CINDY LOPEZ","votes":44},{"id":"999566","consName":"CHULA VISTA-VBM","candidate":"CINDY LOPEZ","votes":0},{"id":"999567","consName":"CHULA VISTA-VBM","candidate":"CINDY LOPEZ","votes":1},{"id":"999568","consName":"CHULA VISTA-VBM","candidate":"CINDY LOPEZ","votes":0},{"id":"999569","consName":"CHULA VISTA-VBM","candidate":"CINDY LOPEZ","votes":0},{"id":"999574","consName":"CHULA VISTA-VBM","candidate":"CINDY LOPEZ","votes":0},{"id":"999575","consName":"CHULA VISTA-VBM","candidate":"CINDY LOPEZ","votes":0},{"id":"999579","consName":"NATIONAL CITY-VBM","candidate":"CINDY LOPEZ","votes":0},{"id":"999580","consName":"NATIONAL CITY-VBM","candidate":"CINDY LOPEZ","votes":19},{"id":"999594","consName":"UNINCORPORATED-VBM","candidate":"CINDY LOPEZ","votes":1},{"id":"999787","consName":"UNINCORPORATED-VBM","candidate":"CINDY LOPEZ","votes":0},{"id":"999789","consName":"UNINCORPORATED-VBM","candidate":"CINDY LOPEZ","votes":0},{"id":"999792","consName":"UNINCORPORATED-VBM","candidate":"CINDY LOPEZ","votes":0},{"id":"999797","consName":"CHULA VISTA-VBM","candidate":"CINDY LOPEZ","votes":11},{"id":"999798","consName":"CHULA VISTA-VBM","candidate":"CINDY LOPEZ","votes":0},{"id":"999799","consName":"CHULA VISTA-VBM","candidate":"CINDY LOPEZ","votes":0},{"id":"999807","consName":"UNINCORPORATED-VBM","candidate":"CINDY LOPEZ","votes":21},{"id":"999808","consName":"VBM-AV","candidate":"CINDY LOPEZ","votes":0},{"id":"999813","consName":"UNINCORPORATED-VBM","candidate":"CINDY LOPEZ","votes":0},{"id":"999817","consName":"UNINCORPORATED-VBM","candidate":"CINDY LOPEZ","votes":0},{"id":"999827","consName":"CHULA VISTA-VBM","candidate":"CINDY LOPEZ","votes":0},{"id":"999828","consName":"CHULA VISTA-VBM","candidate":"CINDY LOPEZ","votes":0},{"id":"999829","consName":"CHULA VISTA-VBM","candidate":"CINDY LOPEZ","votes":0},{"id":"999830","consName":"VBM-AV","candidate":"CINDY LOPEZ","votes":0},{"id":"999834","consName":"CHULA VISTA-VBM","candidate":"CINDY LOPEZ","votes":0},{"id":"999835","consName":"CHULA VISTA-VBM","candidate":"CINDY LOPEZ","votes":0},{"id":"999836","consName":"CHULA VISTA-VBM","candidate":"CINDY LOPEZ","votes":0},{"id":"999837","consName":"CHULA VISTA-VBM","candidate":"CINDY LOPEZ","votes":0},{"id":"999838","consName":"CHULA VISTA-VBM","candidate":"CINDY LOPEZ","votes":0},{"id":"999839","consName":"CHULA VISTA-VBM","candidate":"CINDY LOPEZ","votes":0},{"id":"501600","consName":"SPRING VALLEY","candidate":"SANDRA \"SANDI\" L. SMITH","votes":21},{"id":"501720","consName":"SPRING VALLEY","candidate":"SANDRA \"SANDI\" L. SMITH","votes":934},{"id":"510720","consName":"BONITA","candidate":"SANDRA \"SANDI\" L. SMITH","votes":205},{"id":"518800","consName":"NATIONAL CITY","candidate":"SANDRA \"SANDI\" L. SMITH","votes":123},{"id":"525250","consName":"CHULA VISTA","candidate":"SANDRA \"SANDI\" L. SMITH","votes":240},{"id":"525260","consName":"CHULA VISTA","candidate":"SANDRA \"SANDI\" L. SMITH","votes":527},{"id":"525400","consName":"CHULA VISTA","candidate":"SANDRA \"SANDI\" L. SMITH","votes":262},{"id":"526410","consName":"CHULA VISTA","candidate":"SANDRA \"SANDI\" L. SMITH","votes":437},{"id":"527700","consName":"CHULA VISTA","candidate":"SANDRA \"SANDI\" L. SMITH","votes":831},{"id":"528820","consName":"CHULA VISTA","candidate":"SANDRA \"SANDI\" L. SMITH","votes":269},{"id":"528900","consName":"CHULA VISTA","candidate":"SANDRA \"SANDI\" L. SMITH","votes":164},{"id":"528960","consName":"CHULA VISTA","candidate":"SANDRA \"SANDI\" L. SMITH","votes":533},{"id":"529520","consName":"CHULA VISTA","candidate":"SANDRA \"SANDI\" L. SMITH","votes":689},{"id":"529810","consName":"CHULA VISTA","candidate":"SANDRA \"SANDI\" L. SMITH","votes":301},{"id":"530500","consName":"CHULA VISTA","candidate":"SANDRA \"SANDI\" L. SMITH","votes":65},{"id":"530510","consName":"CHULA VISTA","candidate":"SANDRA \"SANDI\" L. SMITH","votes":63},{"id":"532500","consName":"CHULA VISTA","candidate":"SANDRA \"SANDI\" L. SMITH","votes":202},{"id":"532510","consName":"CHULA VISTA","candidate":"SANDRA \"SANDI\" L. SMITH","votes":36},{"id":"532570","consName":"CHULA VISTA","candidate":"SANDRA \"SANDI\" L. SMITH","votes":354},{"id":"999559","consName":"UNINCORPORATED-VBM","candidate":"SANDRA \"SANDI\" L. SMITH","votes":25},{"id":"999566","consName":"CHULA VISTA-VBM","candidate":"SANDRA \"SANDI\" L. SMITH","votes":0},{"id":"999567","consName":"CHULA VISTA-VBM","candidate":"SANDRA \"SANDI\" L. SMITH","votes":0},{"id":"999568","consName":"CHULA VISTA-VBM","candidate":"SANDRA \"SANDI\" L. SMITH","votes":0},{"id":"999569","consName":"CHULA VISTA-VBM","candidate":"SANDRA \"SANDI\" L. SMITH","votes":1},{"id":"999574","consName":"CHULA VISTA-VBM","candidate":"SANDRA \"SANDI\" L. SMITH","votes":0},{"id":"999575","consName":"CHULA VISTA-VBM","candidate":"SANDRA \"SANDI\" L. SMITH","votes":0},{"id":"999579","consName":"NATIONAL CITY-VBM","candidate":"SANDRA \"SANDI\" L. SMITH","votes":0},{"id":"999580","consName":"NATIONAL CITY-VBM","candidate":"SANDRA \"SANDI\" L. SMITH","votes":8},{"id":"999594","consName":"UNINCORPORATED-VBM","candidate":"SANDRA \"SANDI\" L. SMITH","votes":0},{"id":"999787","consName":"UNINCORPORATED-VBM","candidate":"SANDRA \"SANDI\" L. SMITH","votes":0},{"id":"999789","consName":"UNINCORPORATED-VBM","candidate":"SANDRA \"SANDI\" L. SMITH","votes":0},{"id":"999792","consName":"UNINCORPORATED-VBM","candidate":"SANDRA \"SANDI\" L. SMITH","votes":0},{"id":"999797","consName":"CHULA VISTA-VBM","candidate":"SANDRA \"SANDI\" L. SMITH","votes":8},{"id":"999798","consName":"CHULA VISTA-VBM","candidate":"SANDRA \"SANDI\" L. SMITH","votes":0},{"id":"999799","consName":"CHULA VISTA-VBM","candidate":"SANDRA \"SANDI\" L. SMITH","votes":0},{"id":"999807","consName":"UNINCORPORATED-VBM","candidate":"SANDRA \"SANDI\" L. SMITH","votes":20},{"id":"999808","consName":"VBM-AV","candidate":"SANDRA \"SANDI\" L. SMITH","votes":0},{"id":"999813","consName":"UNINCORPORATED-VBM","candidate":"SANDRA \"SANDI\" L. SMITH","votes":0},{"id":"999817","consName":"UNINCORPORATED-VBM","candidate":"SANDRA \"SANDI\" L. SMITH","votes":0},{"id":"999827","consName":"CHULA VISTA-VBM","candidate":"SANDRA \"SANDI\" L. SMITH","votes":0},{"id":"999828","consName":"CHULA VISTA-VBM","candidate":"SANDRA \"SANDI\" L. SMITH","votes":0},{"id":"999829","consName":"CHULA VISTA-VBM","candidate":"SANDRA \"SANDI\" L. SMITH","votes":0},{"id":"999830","consName":"VBM-AV","candidate":"SANDRA \"SANDI\" L. SMITH","votes":0},{"id":"999834","consName":"CHULA VISTA-VBM","candidate":"SANDRA \"SANDI\" L. SMITH","votes":0},{"id":"999835","consName":"CHULA VISTA-VBM","candidate":"SANDRA \"SANDI\" L. SMITH","votes":0},{"id":"999836","consName":"CHULA VISTA-VBM","candidate":"SANDRA \"SANDI\" L. SMITH","votes":0},{"id":"999837","consName":"CHULA VISTA-VBM","candidate":"SANDRA \"SANDI\" L. SMITH","votes":0},{"id":"999838","consName":"CHULA VISTA-VBM","candidate":"SANDRA \"SANDI\" L. SMITH","votes":0},{"id":"999839","consName":"CHULA VISTA-VBM","candidate":"SANDRA \"SANDI\" L. SMITH","votes":0}]}